{
  "dataset_name": "prices_da",
  "country": "CZ",
  "year": 2019,
  "entsoe_codes_used": [
    "CZ"
  ],
  "start_utc": "2019-01-01 00:00:00+00:00",
  "end_utc": "2019-12-31 23:00:00+00:00",
  "download_timestamp_utc": "2026-02-10T01:06:25.254298+00:00",
  "n_rows_raw": 8760,
  "source_frequency_detected": "unknown",
  "resampling_applied": false,
  "resampling_method": "none",
  "duplicate_count": 0,
  "missing_count": 1,
  "missing_share": 0.00011415525114155251,
  "n_rows_after_normalization": 8760,
  "sha256_of_parquet_file": "bfdef6e2298f47269cad119c72508cae8ea95ccbaec9d81791db266e4bdb6043"
}